reftools/__init__.py
reftools/_computephotpars.cp313-win_amd64.pyd
reftools/getphotpars.py
reftools/graphfile.py
reftools/graphtab.py
reftools/imphtcomp.py
reftools/interpretdq.py
reftools/makedxy.py
reftools/makesmall.py
reftools/mkimphttab.py
reftools/pctetab.py
reftools/tdspysyn.py
reftools/version.py
reftools/data/dqflags_acs.txt
reftools/data/dqflags_hstgen.txt
reftools/data/dqflags_wfc3.txt
reftools/data/pctetab/pctetab_chgleak_110425.txt
reftools/data/pctetab/pctetab_chgleak_110718-1.txt
reftools/data/pctetab/pctetab_chgleak_110718-2.txt
reftools/data/pctetab/pctetab_chgleak_111129-1.txt
reftools/data/pctetab/pctetab_chgleak_111129-2.txt
reftools/data/pctetab/pctetab_column_scaling_111129.txt
reftools/data/pctetab/pctetab_column_scaling_111214.txt
reftools/data/pctetab/pctetab_column_scaling_120119.txt
reftools/data/pctetab/pctetab_column_scaling_130813.txt
reftools/data/pctetab/pctetab_dtdel_110425.txt
reftools/data/pctetab/pctetab_dtdel_111129.txt
reftools/data/pctetab/pctetab_history.txt
reftools/data/pctetab/pctetab_levels_110425.txt
reftools/data/pctetab/pctetab_levels_111129.txt
reftools/data/pctetab/pctetab_scaling_110718.txt
reftools/data/pctetab/pctetab_scaling_110818.txt
reftools/tests/__init__.py
reftools/tests/test_get_phot_pars.py
reftools/tests/test_imphtcomp.py
reftools/tests/test_interpretdq.py
reftools/tests/test_mkimphttab.py
reftools/tests/data/acs_sbc_dev_imp.fits
reftools/tests/data/test_acs_wfc1_dev_imp.fits
reftools/tests/data/test_wfc1_dev_imp.fits
reftools-2.2.0.dist-info/LICENSE.txt
reftools-2.2.0.dist-info/METADATA
reftools-2.2.0.dist-info/WHEEL
reftools-2.2.0.dist-info/entry_points.txt
reftools-2.2.0.dist-info/top_level.txt
reftools-2.2.0.dist-info/RECORD
